package com.chelpus.root.utils;

public class testcore
{
  /* Error */
  public static void main(String[] paramArrayOfString)
  {
    // Byte code:
    //   0: new 6	com/chelpus/root/utils/testcore$1
    //   3: dup
    //   4: invokespecial 18	com/chelpus/root/utils/testcore$1:<init>	()V
    //   7: invokestatic 24	com/chelpus/Utils:startRootJava	(Ljava/lang/Object;)V
    //   10: aconst_null
    //   11: astore 9
    //   13: aconst_null
    //   14: astore 8
    //   16: bipush 16
    //   18: newarray <illegal type>
    //   20: astore 11
    //   22: aload 11
    //   24: dup
    //   25: iconst_0
    //   26: ldc 25
    //   28: bastore
    //   29: dup
    //   30: iconst_1
    //   31: ldc 26
    //   33: bastore
    //   34: dup
    //   35: iconst_2
    //   36: ldc 27
    //   38: bastore
    //   39: dup
    //   40: iconst_3
    //   41: ldc 28
    //   43: bastore
    //   44: dup
    //   45: iconst_4
    //   46: ldc 25
    //   48: bastore
    //   49: dup
    //   50: iconst_5
    //   51: ldc 26
    //   53: bastore
    //   54: dup
    //   55: bipush 6
    //   57: ldc 29
    //   59: bastore
    //   60: dup
    //   61: bipush 7
    //   63: ldc 28
    //   65: bastore
    //   66: dup
    //   67: bipush 8
    //   69: ldc 30
    //   71: bastore
    //   72: dup
    //   73: bipush 9
    //   75: ldc 31
    //   77: bastore
    //   78: dup
    //   79: bipush 10
    //   81: ldc 30
    //   83: bastore
    //   84: dup
    //   85: bipush 11
    //   87: ldc 32
    //   89: bastore
    //   90: dup
    //   91: bipush 12
    //   93: ldc 30
    //   95: bastore
    //   96: dup
    //   97: bipush 13
    //   99: ldc 32
    //   101: bastore
    //   102: dup
    //   103: bipush 14
    //   105: ldc 33
    //   107: bastore
    //   108: dup
    //   109: bipush 15
    //   111: ldc 32
    //   113: bastore
    //   114: pop
    //   115: bipush 24
    //   117: newarray <illegal type>
    //   119: astore 12
    //   121: aload 12
    //   123: dup
    //   124: iconst_0
    //   125: ldc 30
    //   127: bastore
    //   128: dup
    //   129: iconst_1
    //   130: ldc 26
    //   132: bastore
    //   133: dup
    //   134: iconst_2
    //   135: ldc 34
    //   137: bastore
    //   138: dup
    //   139: iconst_3
    //   140: ldc 26
    //   142: bastore
    //   143: dup
    //   144: iconst_4
    //   145: ldc 26
    //   147: bastore
    //   148: dup
    //   149: iconst_5
    //   150: ldc 26
    //   152: bastore
    //   153: dup
    //   154: bipush 6
    //   156: ldc 35
    //   158: bastore
    //   159: dup
    //   160: bipush 7
    //   162: ldc 26
    //   164: bastore
    //   165: dup
    //   166: bipush 8
    //   168: ldc 26
    //   170: bastore
    //   171: dup
    //   172: bipush 9
    //   174: ldc 26
    //   176: bastore
    //   177: dup
    //   178: bipush 10
    //   180: ldc 35
    //   182: bastore
    //   183: dup
    //   184: bipush 11
    //   186: ldc 26
    //   188: bastore
    //   189: dup
    //   190: bipush 12
    //   192: ldc 26
    //   194: bastore
    //   195: dup
    //   196: bipush 13
    //   198: ldc 26
    //   200: bastore
    //   201: dup
    //   202: bipush 14
    //   204: ldc 36
    //   206: bastore
    //   207: dup
    //   208: bipush 15
    //   210: ldc 26
    //   212: bastore
    //   213: dup
    //   214: bipush 16
    //   216: ldc 26
    //   218: bastore
    //   219: dup
    //   220: bipush 17
    //   222: ldc 26
    //   224: bastore
    //   225: dup
    //   226: bipush 18
    //   228: ldc 26
    //   230: bastore
    //   231: dup
    //   232: bipush 19
    //   234: ldc 26
    //   236: bastore
    //   237: dup
    //   238: bipush 20
    //   240: ldc 37
    //   242: bastore
    //   243: dup
    //   244: bipush 21
    //   246: ldc 26
    //   248: bastore
    //   249: dup
    //   250: bipush 22
    //   252: ldc 38
    //   254: bastore
    //   255: dup
    //   256: bipush 23
    //   258: ldc 39
    //   260: bastore
    //   261: pop
    //   262: bipush 19
    //   264: newarray <illegal type>
    //   266: astore 13
    //   268: aload 13
    //   270: dup
    //   271: iconst_0
    //   272: ldc 40
    //   274: bastore
    //   275: dup
    //   276: iconst_1
    //   277: ldc 28
    //   279: bastore
    //   280: dup
    //   281: iconst_2
    //   282: ldc 25
    //   284: bastore
    //   285: dup
    //   286: iconst_3
    //   287: ldc 26
    //   289: bastore
    //   290: dup
    //   291: iconst_4
    //   292: ldc 26
    //   294: bastore
    //   295: dup
    //   296: iconst_5
    //   297: ldc 26
    //   299: bastore
    //   300: dup
    //   301: bipush 6
    //   303: ldc 26
    //   305: bastore
    //   306: dup
    //   307: bipush 7
    //   309: ldc 26
    //   311: bastore
    //   312: dup
    //   313: bipush 8
    //   315: ldc 26
    //   317: bastore
    //   318: dup
    //   319: bipush 9
    //   321: ldc 26
    //   323: bastore
    //   324: dup
    //   325: bipush 10
    //   327: ldc 26
    //   329: bastore
    //   330: dup
    //   331: bipush 11
    //   333: ldc 26
    //   335: bastore
    //   336: dup
    //   337: bipush 12
    //   339: ldc 26
    //   341: bastore
    //   342: dup
    //   343: bipush 13
    //   345: ldc 26
    //   347: bastore
    //   348: dup
    //   349: bipush 14
    //   351: ldc 41
    //   353: bastore
    //   354: dup
    //   355: bipush 15
    //   357: ldc 42
    //   359: bastore
    //   360: dup
    //   361: bipush 16
    //   363: ldc 26
    //   365: bastore
    //   366: dup
    //   367: bipush 17
    //   369: ldc 26
    //   371: bastore
    //   372: dup
    //   373: bipush 18
    //   375: ldc 35
    //   377: bastore
    //   378: pop
    //   379: new 44	java/io/File
    //   382: dup
    //   383: ldc 46
    //   385: invokespecial 49	java/io/File:<init>	(Ljava/lang/String;)V
    //   388: astore_0
    //   389: aload_0
    //   390: invokevirtual 53	java/io/File:exists	()Z
    //   393: ifne +827 -> 1220
    //   396: bipush 6
    //   398: anewarray 55	java/lang/String
    //   401: astore 14
    //   403: aload 14
    //   405: iconst_0
    //   406: ldc 57
    //   408: aastore
    //   409: aload 14
    //   411: iconst_1
    //   412: ldc 59
    //   414: aastore
    //   415: aload 14
    //   417: iconst_2
    //   418: ldc 61
    //   420: aastore
    //   421: aload 14
    //   423: iconst_3
    //   424: ldc 63
    //   426: aastore
    //   427: aload 14
    //   429: iconst_4
    //   430: ldc 65
    //   432: aastore
    //   433: aload 14
    //   435: iconst_5
    //   436: ldc 67
    //   438: aastore
    //   439: aload 14
    //   441: arraylength
    //   442: istore_2
    //   443: iconst_0
    //   444: istore_1
    //   445: aload_0
    //   446: astore 7
    //   448: aload 7
    //   450: astore_0
    //   451: iload_1
    //   452: iload_2
    //   453: if_icmpge +111 -> 564
    //   456: aload 14
    //   458: iload_1
    //   459: aaload
    //   460: astore_0
    //   461: aload 7
    //   463: astore 8
    //   465: aload 7
    //   467: astore 9
    //   469: new 44	java/io/File
    //   472: dup
    //   473: new 69	java/lang/StringBuilder
    //   476: dup
    //   477: invokespecial 70	java/lang/StringBuilder:<init>	()V
    //   480: aload_0
    //   481: invokevirtual 74	java/lang/StringBuilder:append	(Ljava/lang/String;)Ljava/lang/StringBuilder;
    //   484: ldc 76
    //   486: invokevirtual 74	java/lang/StringBuilder:append	(Ljava/lang/String;)Ljava/lang/StringBuilder;
    //   489: invokevirtual 80	java/lang/StringBuilder:toString	()Ljava/lang/String;
    //   492: invokespecial 49	java/io/File:<init>	(Ljava/lang/String;)V
    //   495: astore 10
    //   497: aload 7
    //   499: astore 8
    //   501: aload 7
    //   503: astore 9
    //   505: aload 7
    //   507: astore_0
    //   508: aload 10
    //   510: invokevirtual 53	java/io/File:exists	()Z
    //   513: ifeq +697 -> 1210
    //   516: aload 7
    //   518: astore 8
    //   520: aload 7
    //   522: astore 9
    //   524: getstatic 86	java/lang/System:out	Ljava/io/PrintStream;
    //   527: new 69	java/lang/StringBuilder
    //   530: dup
    //   531: invokespecial 70	java/lang/StringBuilder:<init>	()V
    //   534: ldc 88
    //   536: invokevirtual 74	java/lang/StringBuilder:append	(Ljava/lang/String;)Ljava/lang/StringBuilder;
    //   539: aload 10
    //   541: invokevirtual 89	java/io/File:toString	()Ljava/lang/String;
    //   544: invokevirtual 74	java/lang/StringBuilder:append	(Ljava/lang/String;)Ljava/lang/StringBuilder;
    //   547: ldc 91
    //   549: invokevirtual 74	java/lang/StringBuilder:append	(Ljava/lang/String;)Ljava/lang/StringBuilder;
    //   552: invokevirtual 80	java/lang/StringBuilder:toString	()Ljava/lang/String;
    //   555: invokevirtual 96	java/io/PrintStream:println	(Ljava/lang/String;)V
    //   558: aload 10
    //   560: astore_0
    //   561: goto +649 -> 1210
    //   564: aload_0
    //   565: astore 8
    //   567: aload_0
    //   568: astore 9
    //   570: aload_0
    //   571: invokevirtual 53	java/io/File:exists	()Z
    //   574: ifne +83 -> 657
    //   577: aload_0
    //   578: astore 8
    //   580: aload_0
    //   581: astore 9
    //   583: new 15	java/io/FileNotFoundException
    //   586: dup
    //   587: invokespecial 97	java/io/FileNotFoundException:<init>	()V
    //   590: athrow
    //   591: astore_0
    //   592: getstatic 86	java/lang/System:out	Ljava/io/PrintStream;
    //   595: ldc 99
    //   597: invokevirtual 96	java/io/PrintStream:println	(Ljava/lang/String;)V
    //   600: aload 8
    //   602: astore_0
    //   603: ldc 101
    //   605: invokestatic 105	com/chelpus/Utils:getFileDalvikCacheName	(Ljava/lang/String;)Ljava/io/File;
    //   608: invokevirtual 53	java/io/File:exists	()Z
    //   611: ifne +200 -> 811
    //   614: new 44	java/io/File
    //   617: dup
    //   618: ldc 107
    //   620: invokespecial 49	java/io/File:<init>	(Ljava/lang/String;)V
    //   623: astore 7
    //   625: aload 7
    //   627: astore_0
    //   628: aload 7
    //   630: invokevirtual 53	java/io/File:exists	()Z
    //   633: ifne +178 -> 811
    //   636: new 15	java/io/FileNotFoundException
    //   639: dup
    //   640: invokespecial 97	java/io/FileNotFoundException:<init>	()V
    //   643: athrow
    //   644: astore_0
    //   645: getstatic 86	java/lang/System:out	Ljava/io/PrintStream;
    //   648: ldc 99
    //   650: invokevirtual 96	java/io/PrintStream:println	(Ljava/lang/String;)V
    //   653: invokestatic 110	com/chelpus/Utils:exitFromRootJava	()V
    //   656: return
    //   657: aload_0
    //   658: astore 8
    //   660: aload_0
    //   661: astore 9
    //   663: new 44	java/io/File
    //   666: dup
    //   667: ldc 112
    //   669: invokespecial 49	java/io/File:<init>	(Ljava/lang/String;)V
    //   672: astore 7
    //   674: aload_0
    //   675: astore 8
    //   677: aload_0
    //   678: astore 9
    //   680: new 44	java/io/File
    //   683: dup
    //   684: ldc 114
    //   686: invokespecial 49	java/io/File:<init>	(Ljava/lang/String;)V
    //   689: astore 10
    //   691: aload_0
    //   692: astore 8
    //   694: aload_0
    //   695: astore 9
    //   697: new 44	java/io/File
    //   700: dup
    //   701: ldc 116
    //   703: invokespecial 49	java/io/File:<init>	(Ljava/lang/String;)V
    //   706: astore 14
    //   708: aload_0
    //   709: astore 8
    //   711: aload_0
    //   712: astore 9
    //   714: new 44	java/io/File
    //   717: dup
    //   718: ldc 118
    //   720: invokespecial 49	java/io/File:<init>	(Ljava/lang/String;)V
    //   723: astore 15
    //   725: aload_0
    //   726: astore 8
    //   728: aload_0
    //   729: astore 9
    //   731: aload 7
    //   733: invokevirtual 121	java/io/File:delete	()Z
    //   736: pop
    //   737: aload_0
    //   738: astore 8
    //   740: aload_0
    //   741: astore 9
    //   743: aload 10
    //   745: invokevirtual 121	java/io/File:delete	()Z
    //   748: pop
    //   749: aload_0
    //   750: astore 8
    //   752: aload_0
    //   753: astore 9
    //   755: aload 14
    //   757: invokevirtual 121	java/io/File:delete	()Z
    //   760: pop
    //   761: aload_0
    //   762: astore 8
    //   764: aload_0
    //   765: astore 9
    //   767: aload 15
    //   769: invokevirtual 121	java/io/File:delete	()Z
    //   772: pop
    //   773: goto -170 -> 603
    //   776: astore_0
    //   777: getstatic 86	java/lang/System:out	Ljava/io/PrintStream;
    //   780: new 69	java/lang/StringBuilder
    //   783: dup
    //   784: invokespecial 70	java/lang/StringBuilder:<init>	()V
    //   787: ldc 123
    //   789: invokevirtual 74	java/lang/StringBuilder:append	(Ljava/lang/String;)Ljava/lang/StringBuilder;
    //   792: aload_0
    //   793: invokevirtual 124	java/lang/Exception:toString	()Ljava/lang/String;
    //   796: invokevirtual 74	java/lang/StringBuilder:append	(Ljava/lang/String;)Ljava/lang/StringBuilder;
    //   799: invokevirtual 80	java/lang/StringBuilder:toString	()Ljava/lang/String;
    //   802: invokevirtual 96	java/io/PrintStream:println	(Ljava/lang/String;)V
    //   805: aload 9
    //   807: astore_0
    //   808: goto -205 -> 603
    //   811: new 44	java/io/File
    //   814: dup
    //   815: ldc 118
    //   817: invokespecial 49	java/io/File:<init>	(Ljava/lang/String;)V
    //   820: astore 7
    //   822: aload 7
    //   824: invokevirtual 121	java/io/File:delete	()Z
    //   827: pop
    //   828: new 126	java/io/RandomAccessFile
    //   831: dup
    //   832: aload_0
    //   833: ldc -128
    //   835: invokespecial 131	java/io/RandomAccessFile:<init>	(Ljava/io/File;Ljava/lang/String;)V
    //   838: invokevirtual 135	java/io/RandomAccessFile:getChannel	()Ljava/nio/channels/FileChannel;
    //   841: astore_0
    //   842: aload_0
    //   843: getstatic 141	java/nio/channels/FileChannel$MapMode:READ_ONLY	Ljava/nio/channels/FileChannel$MapMode;
    //   846: lconst_0
    //   847: aload_0
    //   848: invokevirtual 147	java/nio/channels/FileChannel:size	()J
    //   851: l2i
    //   852: i2l
    //   853: invokevirtual 151	java/nio/channels/FileChannel:map	(Ljava/nio/channels/FileChannel$MapMode;JJ)Ljava/nio/MappedByteBuffer;
    //   856: astore 8
    //   858: lconst_0
    //   859: lstore 5
    //   861: aload 8
    //   863: invokevirtual 156	java/nio/MappedByteBuffer:hasRemaining	()Z
    //   866: ifeq +278 -> 1144
    //   869: aload 8
    //   871: invokevirtual 160	java/nio/MappedByteBuffer:position	()I
    //   874: istore_3
    //   875: aload 8
    //   877: invokevirtual 164	java/nio/MappedByteBuffer:get	()B
    //   880: istore 4
    //   882: iload 4
    //   884: aload 11
    //   886: iconst_0
    //   887: baload
    //   888: if_icmpne +57 -> 945
    //   891: iconst_1
    //   892: istore_1
    //   893: aload 8
    //   895: iload_3
    //   896: iconst_1
    //   897: iadd
    //   898: invokevirtual 167	java/nio/MappedByteBuffer:position	(I)Ljava/nio/Buffer;
    //   901: pop
    //   902: aload 8
    //   904: invokevirtual 164	java/nio/MappedByteBuffer:get	()B
    //   907: istore_2
    //   908: goto +315 -> 1223
    //   911: iload_1
    //   912: iconst_1
    //   913: iadd
    //   914: istore_1
    //   915: iload_1
    //   916: aload 11
    //   918: arraylength
    //   919: if_icmpne +170 -> 1089
    //   922: getstatic 86	java/lang/System:out	Ljava/io/PrintStream;
    //   925: ldc -87
    //   927: invokevirtual 96	java/io/PrintStream:println	(Ljava/lang/String;)V
    //   930: aload 7
    //   932: invokevirtual 172	java/io/File:createNewFile	()Z
    //   935: pop
    //   936: aload 8
    //   938: iload_3
    //   939: iconst_1
    //   940: iadd
    //   941: invokevirtual 167	java/nio/MappedByteBuffer:position	(I)Ljava/nio/Buffer;
    //   944: pop
    //   945: iload 4
    //   947: aload 12
    //   949: iconst_0
    //   950: baload
    //   951: if_icmpne +57 -> 1008
    //   954: iconst_1
    //   955: istore_1
    //   956: aload 8
    //   958: iload_3
    //   959: iconst_1
    //   960: iadd
    //   961: invokevirtual 167	java/nio/MappedByteBuffer:position	(I)Ljava/nio/Buffer;
    //   964: pop
    //   965: aload 8
    //   967: invokevirtual 164	java/nio/MappedByteBuffer:get	()B
    //   970: istore_2
    //   971: goto +363 -> 1334
    //   974: iload_1
    //   975: iconst_1
    //   976: iadd
    //   977: istore_1
    //   978: iload_1
    //   979: aload 12
    //   981: arraylength
    //   982: if_icmpne +116 -> 1098
    //   985: getstatic 86	java/lang/System:out	Ljava/io/PrintStream;
    //   988: ldc -87
    //   990: invokevirtual 96	java/io/PrintStream:println	(Ljava/lang/String;)V
    //   993: aload 7
    //   995: invokevirtual 172	java/io/File:createNewFile	()Z
    //   998: pop
    //   999: aload 8
    //   1001: iload_3
    //   1002: iconst_1
    //   1003: iadd
    //   1004: invokevirtual 167	java/nio/MappedByteBuffer:position	(I)Ljava/nio/Buffer;
    //   1007: pop
    //   1008: iload 4
    //   1010: aload 13
    //   1012: iconst_0
    //   1013: baload
    //   1014: if_icmpne +57 -> 1071
    //   1017: iconst_1
    //   1018: istore_1
    //   1019: aload 8
    //   1021: iload_3
    //   1022: iconst_1
    //   1023: iadd
    //   1024: invokevirtual 167	java/nio/MappedByteBuffer:position	(I)Ljava/nio/Buffer;
    //   1027: pop
    //   1028: aload 8
    //   1030: invokevirtual 164	java/nio/MappedByteBuffer:get	()B
    //   1033: istore_2
    //   1034: goto +459 -> 1493
    //   1037: iload_1
    //   1038: iconst_1
    //   1039: iadd
    //   1040: istore_1
    //   1041: iload_1
    //   1042: aload 13
    //   1044: arraylength
    //   1045: if_icmpne +62 -> 1107
    //   1048: getstatic 86	java/lang/System:out	Ljava/io/PrintStream;
    //   1051: ldc -87
    //   1053: invokevirtual 96	java/io/PrintStream:println	(Ljava/lang/String;)V
    //   1056: aload 7
    //   1058: invokevirtual 172	java/io/File:createNewFile	()Z
    //   1061: pop
    //   1062: aload 8
    //   1064: iload_3
    //   1065: iconst_1
    //   1066: iadd
    //   1067: invokevirtual 167	java/nio/MappedByteBuffer:position	(I)Ljava/nio/Buffer;
    //   1070: pop
    //   1071: aload 8
    //   1073: iload_3
    //   1074: iconst_1
    //   1075: iadd
    //   1076: invokevirtual 167	java/nio/MappedByteBuffer:position	(I)Ljava/nio/Buffer;
    //   1079: pop
    //   1080: lload 5
    //   1082: lconst_1
    //   1083: ladd
    //   1084: lstore 5
    //   1086: goto -225 -> 861
    //   1089: aload 8
    //   1091: invokevirtual 164	java/nio/MappedByteBuffer:get	()B
    //   1094: istore_2
    //   1095: goto +128 -> 1223
    //   1098: aload 8
    //   1100: invokevirtual 164	java/nio/MappedByteBuffer:get	()B
    //   1103: istore_2
    //   1104: goto +230 -> 1334
    //   1107: aload 8
    //   1109: invokevirtual 164	java/nio/MappedByteBuffer:get	()B
    //   1112: istore_2
    //   1113: goto +380 -> 1493
    //   1116: astore 7
    //   1118: getstatic 86	java/lang/System:out	Ljava/io/PrintStream;
    //   1121: new 69	java/lang/StringBuilder
    //   1124: dup
    //   1125: invokespecial 70	java/lang/StringBuilder:<init>	()V
    //   1128: ldc -82
    //   1130: invokevirtual 74	java/lang/StringBuilder:append	(Ljava/lang/String;)Ljava/lang/StringBuilder;
    //   1133: aload 7
    //   1135: invokevirtual 177	java/lang/StringBuilder:append	(Ljava/lang/Object;)Ljava/lang/StringBuilder;
    //   1138: invokevirtual 80	java/lang/StringBuilder:toString	()Ljava/lang/String;
    //   1141: invokevirtual 96	java/io/PrintStream:println	(Ljava/lang/String;)V
    //   1144: aload_0
    //   1145: invokevirtual 180	java/nio/channels/FileChannel:close	()V
    //   1148: goto -495 -> 653
    //   1151: astore_0
    //   1152: getstatic 86	java/lang/System:out	Ljava/io/PrintStream;
    //   1155: new 69	java/lang/StringBuilder
    //   1158: dup
    //   1159: invokespecial 70	java/lang/StringBuilder:<init>	()V
    //   1162: ldc 123
    //   1164: invokevirtual 74	java/lang/StringBuilder:append	(Ljava/lang/String;)Ljava/lang/StringBuilder;
    //   1167: aload_0
    //   1168: invokevirtual 124	java/lang/Exception:toString	()Ljava/lang/String;
    //   1171: invokevirtual 74	java/lang/StringBuilder:append	(Ljava/lang/String;)Ljava/lang/StringBuilder;
    //   1174: invokevirtual 80	java/lang/StringBuilder:toString	()Ljava/lang/String;
    //   1177: invokevirtual 96	java/io/PrintStream:println	(Ljava/lang/String;)V
    //   1180: goto -527 -> 653
    //   1183: astore_0
    //   1184: goto -32 -> 1152
    //   1187: astore_0
    //   1188: goto -543 -> 645
    //   1191: astore 7
    //   1193: aload_0
    //   1194: astore 9
    //   1196: aload 7
    //   1198: astore_0
    //   1199: goto -422 -> 777
    //   1202: astore 7
    //   1204: aload_0
    //   1205: astore 8
    //   1207: goto -615 -> 592
    //   1210: iload_1
    //   1211: iconst_1
    //   1212: iadd
    //   1213: istore_1
    //   1214: aload_0
    //   1215: astore 7
    //   1217: goto -769 -> 448
    //   1220: goto -656 -> 564
    //   1223: iload_2
    //   1224: aload 11
    //   1226: iload_1
    //   1227: baload
    //   1228: if_icmpeq -317 -> 911
    //   1231: bipush 16
    //   1233: newarray <illegal type>
    //   1235: dup
    //   1236: iconst_0
    //   1237: ldc 28
    //   1239: bastore
    //   1240: dup
    //   1241: iconst_1
    //   1242: ldc -75
    //   1244: bastore
    //   1245: dup
    //   1246: iconst_2
    //   1247: ldc 28
    //   1249: bastore
    //   1250: dup
    //   1251: iconst_3
    //   1252: ldc 28
    //   1254: bastore
    //   1255: dup
    //   1256: iconst_4
    //   1257: ldc 28
    //   1259: bastore
    //   1260: dup
    //   1261: iconst_5
    //   1262: ldc -75
    //   1264: bastore
    //   1265: dup
    //   1266: bipush 6
    //   1268: ldc 28
    //   1270: bastore
    //   1271: dup
    //   1272: bipush 7
    //   1274: ldc 28
    //   1276: bastore
    //   1277: dup
    //   1278: bipush 8
    //   1280: ldc 28
    //   1282: bastore
    //   1283: dup
    //   1284: bipush 9
    //   1286: ldc 28
    //   1288: bastore
    //   1289: dup
    //   1290: bipush 10
    //   1292: ldc 28
    //   1294: bastore
    //   1295: dup
    //   1296: bipush 11
    //   1298: ldc 28
    //   1300: bastore
    //   1301: dup
    //   1302: bipush 12
    //   1304: ldc 28
    //   1306: bastore
    //   1307: dup
    //   1308: bipush 13
    //   1310: ldc 28
    //   1312: bastore
    //   1313: dup
    //   1314: bipush 14
    //   1316: ldc 28
    //   1318: bastore
    //   1319: dup
    //   1320: bipush 15
    //   1322: ldc 28
    //   1324: bastore
    //   1325: iload_1
    //   1326: baload
    //   1327: iconst_1
    //   1328: if_icmpne -392 -> 936
    //   1331: goto -420 -> 911
    //   1334: iload_2
    //   1335: aload 12
    //   1337: iload_1
    //   1338: baload
    //   1339: if_icmpeq -365 -> 974
    //   1342: bipush 24
    //   1344: newarray <illegal type>
    //   1346: dup
    //   1347: iconst_0
    //   1348: ldc 28
    //   1350: bastore
    //   1351: dup
    //   1352: iconst_1
    //   1353: ldc -75
    //   1355: bastore
    //   1356: dup
    //   1357: iconst_2
    //   1358: ldc 28
    //   1360: bastore
    //   1361: dup
    //   1362: iconst_3
    //   1363: ldc -75
    //   1365: bastore
    //   1366: dup
    //   1367: iconst_4
    //   1368: ldc -75
    //   1370: bastore
    //   1371: dup
    //   1372: iconst_5
    //   1373: ldc -75
    //   1375: bastore
    //   1376: dup
    //   1377: bipush 6
    //   1379: ldc 28
    //   1381: bastore
    //   1382: dup
    //   1383: bipush 7
    //   1385: ldc -75
    //   1387: bastore
    //   1388: dup
    //   1389: bipush 8
    //   1391: ldc -75
    //   1393: bastore
    //   1394: dup
    //   1395: bipush 9
    //   1397: ldc -75
    //   1399: bastore
    //   1400: dup
    //   1401: bipush 10
    //   1403: ldc 28
    //   1405: bastore
    //   1406: dup
    //   1407: bipush 11
    //   1409: ldc -75
    //   1411: bastore
    //   1412: dup
    //   1413: bipush 12
    //   1415: ldc -75
    //   1417: bastore
    //   1418: dup
    //   1419: bipush 13
    //   1421: ldc -75
    //   1423: bastore
    //   1424: dup
    //   1425: bipush 14
    //   1427: ldc 28
    //   1429: bastore
    //   1430: dup
    //   1431: bipush 15
    //   1433: ldc -75
    //   1435: bastore
    //   1436: dup
    //   1437: bipush 16
    //   1439: ldc -75
    //   1441: bastore
    //   1442: dup
    //   1443: bipush 17
    //   1445: ldc -75
    //   1447: bastore
    //   1448: dup
    //   1449: bipush 18
    //   1451: ldc -75
    //   1453: bastore
    //   1454: dup
    //   1455: bipush 19
    //   1457: ldc -75
    //   1459: bastore
    //   1460: dup
    //   1461: bipush 20
    //   1463: ldc 28
    //   1465: bastore
    //   1466: dup
    //   1467: bipush 21
    //   1469: ldc -75
    //   1471: bastore
    //   1472: dup
    //   1473: bipush 22
    //   1475: ldc 28
    //   1477: bastore
    //   1478: dup
    //   1479: bipush 23
    //   1481: ldc 28
    //   1483: bastore
    //   1484: iload_1
    //   1485: baload
    //   1486: iconst_1
    //   1487: if_icmpne -488 -> 999
    //   1490: goto -516 -> 974
    //   1493: iload_2
    //   1494: aload 13
    //   1496: iload_1
    //   1497: baload
    //   1498: if_icmpeq -461 -> 1037
    //   1501: bipush 19
    //   1503: newarray <illegal type>
    //   1505: dup
    //   1506: iconst_0
    //   1507: ldc 28
    //   1509: bastore
    //   1510: dup
    //   1511: iconst_1
    //   1512: ldc 28
    //   1514: bastore
    //   1515: dup
    //   1516: iconst_2
    //   1517: ldc 28
    //   1519: bastore
    //   1520: dup
    //   1521: iconst_3
    //   1522: ldc -75
    //   1524: bastore
    //   1525: dup
    //   1526: iconst_4
    //   1527: ldc -75
    //   1529: bastore
    //   1530: dup
    //   1531: iconst_5
    //   1532: ldc -75
    //   1534: bastore
    //   1535: dup
    //   1536: bipush 6
    //   1538: ldc -75
    //   1540: bastore
    //   1541: dup
    //   1542: bipush 7
    //   1544: ldc -75
    //   1546: bastore
    //   1547: dup
    //   1548: bipush 8
    //   1550: ldc -75
    //   1552: bastore
    //   1553: dup
    //   1554: bipush 9
    //   1556: ldc -75
    //   1558: bastore
    //   1559: dup
    //   1560: bipush 10
    //   1562: ldc -75
    //   1564: bastore
    //   1565: dup
    //   1566: bipush 11
    //   1568: ldc -75
    //   1570: bastore
    //   1571: dup
    //   1572: bipush 12
    //   1574: ldc -75
    //   1576: bastore
    //   1577: dup
    //   1578: bipush 13
    //   1580: ldc -75
    //   1582: bastore
    //   1583: dup
    //   1584: bipush 14
    //   1586: ldc 28
    //   1588: bastore
    //   1589: dup
    //   1590: bipush 15
    //   1592: ldc 28
    //   1594: bastore
    //   1595: dup
    //   1596: bipush 16
    //   1598: ldc -75
    //   1600: bastore
    //   1601: dup
    //   1602: bipush 17
    //   1604: ldc -75
    //   1606: bastore
    //   1607: dup
    //   1608: bipush 18
    //   1610: ldc 28
    //   1612: bastore
    //   1613: iload_1
    //   1614: baload
    //   1615: iconst_1
    //   1616: if_icmpne -554 -> 1062
    //   1619: goto -582 -> 1037
    // Local variable table:
    //   start	length	slot	name	signature
    //   0	1622	0	paramArrayOfString	String[]
    //   444	1170	1	i	int
    //   442	1057	2	j	int
    //   874	202	3	k	int
    //   880	135	4	m	int
    //   859	226	5	l	long
    //   446	611	7	localObject1	Object
    //   1116	18	7	localException1	Exception
    //   1191	6	7	localException2	Exception
    //   1202	1	7	localFileNotFoundException	java.io.FileNotFoundException
    //   1215	1	7	arrayOfString	String[]
    //   14	1192	8	localObject2	Object
    //   11	1184	9	localObject3	Object
    //   495	249	10	localFile1	java.io.File
    //   20	1205	11	arrayOfByte1	byte[]
    //   119	1217	12	arrayOfByte2	byte[]
    //   266	1229	13	arrayOfByte3	byte[]
    //   401	355	14	localObject4	Object
    //   723	45	15	localFile2	java.io.File
    // Exception table:
    //   from	to	target	type
    //   379	389	591	java/io/FileNotFoundException
    //   469	497	591	java/io/FileNotFoundException
    //   508	516	591	java/io/FileNotFoundException
    //   524	558	591	java/io/FileNotFoundException
    //   570	577	591	java/io/FileNotFoundException
    //   583	591	591	java/io/FileNotFoundException
    //   663	674	591	java/io/FileNotFoundException
    //   680	691	591	java/io/FileNotFoundException
    //   697	708	591	java/io/FileNotFoundException
    //   714	725	591	java/io/FileNotFoundException
    //   731	737	591	java/io/FileNotFoundException
    //   743	749	591	java/io/FileNotFoundException
    //   755	761	591	java/io/FileNotFoundException
    //   767	773	591	java/io/FileNotFoundException
    //   628	644	644	java/io/FileNotFoundException
    //   811	858	644	java/io/FileNotFoundException
    //   861	882	644	java/io/FileNotFoundException
    //   893	908	644	java/io/FileNotFoundException
    //   915	936	644	java/io/FileNotFoundException
    //   936	945	644	java/io/FileNotFoundException
    //   956	971	644	java/io/FileNotFoundException
    //   978	999	644	java/io/FileNotFoundException
    //   999	1008	644	java/io/FileNotFoundException
    //   1019	1034	644	java/io/FileNotFoundException
    //   1041	1062	644	java/io/FileNotFoundException
    //   1062	1071	644	java/io/FileNotFoundException
    //   1071	1080	644	java/io/FileNotFoundException
    //   1089	1095	644	java/io/FileNotFoundException
    //   1098	1104	644	java/io/FileNotFoundException
    //   1107	1113	644	java/io/FileNotFoundException
    //   1118	1144	644	java/io/FileNotFoundException
    //   1144	1148	644	java/io/FileNotFoundException
    //   379	389	776	java/lang/Exception
    //   469	497	776	java/lang/Exception
    //   508	516	776	java/lang/Exception
    //   524	558	776	java/lang/Exception
    //   570	577	776	java/lang/Exception
    //   583	591	776	java/lang/Exception
    //   663	674	776	java/lang/Exception
    //   680	691	776	java/lang/Exception
    //   697	708	776	java/lang/Exception
    //   714	725	776	java/lang/Exception
    //   731	737	776	java/lang/Exception
    //   743	749	776	java/lang/Exception
    //   755	761	776	java/lang/Exception
    //   767	773	776	java/lang/Exception
    //   861	882	1116	java/lang/Exception
    //   893	908	1116	java/lang/Exception
    //   915	936	1116	java/lang/Exception
    //   936	945	1116	java/lang/Exception
    //   956	971	1116	java/lang/Exception
    //   978	999	1116	java/lang/Exception
    //   999	1008	1116	java/lang/Exception
    //   1019	1034	1116	java/lang/Exception
    //   1041	1062	1116	java/lang/Exception
    //   1062	1071	1116	java/lang/Exception
    //   1071	1080	1116	java/lang/Exception
    //   1089	1095	1116	java/lang/Exception
    //   1098	1104	1116	java/lang/Exception
    //   1107	1113	1116	java/lang/Exception
    //   628	644	1151	java/lang/Exception
    //   811	858	1151	java/lang/Exception
    //   1118	1144	1151	java/lang/Exception
    //   1144	1148	1151	java/lang/Exception
    //   603	625	1183	java/lang/Exception
    //   603	625	1187	java/io/FileNotFoundException
    //   389	403	1191	java/lang/Exception
    //   439	443	1191	java/lang/Exception
    //   389	403	1202	java/io/FileNotFoundException
    //   439	443	1202	java/io/FileNotFoundException
  }
}


/* Location:              /Users/sundayliu/Desktop/gamecheat/com.android.vending.billing.InAppBillingService.LACK-1/classes-dex2jar.jar!/com/chelpus/root/utils/testcore.class
 * Java compiler version: 6 (50.0)
 * JD-Core Version:       0.7.1
 */